[{"id":"340181102001","text":"西街居委会"},{"id":"340181102002","text":"东街居委会"},{"id":"340181102200","text":"兴坝村委会"},{"id":"340181102201","text":"三星村委会"},{"id":"340181102202","text":"建和村委会"},{"id":"340181102203","text":"驷马村委会"},{"id":"340181102204","text":"工民村委会"},{"id":"340181102205","text":"大树刘村委会"},{"id":"340181102206","text":"接引庵村委会"},{"id":"340181102207","text":"锦旗村委会"},{"id":"340181102208","text":"星火村委会"},{"id":"340181102209","text":"合浦村委会"},{"id":"340181102210","text":"峏山村委会"},{"id":"340181102211","text":"板桥村委会"},{"id":"340181102212","text":"大塘村委会"},{"id":"340181102213","text":"汪桥村委会"},{"id":"340181102214","text":"五星村委会"},{"id":"340181102215","text":"双泉村委会"}]