[{"id":"341324109200","text":"黑塔村委会"},{"id":"341324109201","text":"红旗村委会"},{"id":"341324109202","text":"顺河村委会"},{"id":"341324109203","text":"小梁村委会"},{"id":"341324109204","text":"朱山村委会"},{"id":"341324109205","text":"马厂村委会"},{"id":"341324109206","text":"大魏村委会"},{"id":"341324109207","text":"界牌村委会"},{"id":"341324109208","text":"蒋杨村委会"},{"id":"341324109209","text":"倪姚村委会"},{"id":"341324109210","text":"陈圩村委会"},{"id":"341324109211","text":"王武村委会"},{"id":"341324109212","text":"周黄村委会"},{"id":"341324109213","text":"三葛村委会"},{"id":"341324109214","text":"三甄村委会"},{"id":"341324109215","text":"韩徐村委会"},{"id":"341324109216","text":"河西村委会"},{"id":"341324109217","text":"三陈村委会"}]