[{"id":"520525118001","text":"水东社区居民委员会"},{"id":"520525118002","text":"独山社区居民委员会"},{"id":"520525118003","text":"姑箐社区居民委员会"},{"id":"520525118004","text":"麻园社区居民委员会"},{"id":"520525118005","text":"松树坝社区居民委员会"},{"id":"520525118006","text":"木城社区居民委员会"},{"id":"520525118203","text":"沙坝村委会"},{"id":"520525118204","text":"金子村委会"},{"id":"520525118205","text":"滥坝村委会"},{"id":"520525118206","text":"老包底村委会"},{"id":"520525118211","text":"怕那村委会"},{"id":"520525118213","text":"箱子村委会"},{"id":"520525118214","text":"新明村委会"},{"id":"520525118215","text":"烟山村委会"},{"id":"520525118217","text":"簸落村委会"}]