[{"id":"520623105001","text":"京州社区"},{"id":"520623105201","text":"小鸡公村委会"},{"id":"520623105202","text":"大鸡公村委会"},{"id":"520623105203","text":"红溪屯村委会"},{"id":"520623105204","text":"铺沟村委会"},{"id":"520623105205","text":"石阳村委会"},{"id":"520623105206","text":"三道拐村委会"},{"id":"520623105207","text":"团结村委会"},{"id":"520623105208","text":"烂沟村委会"},{"id":"520623105209","text":"杉木岭村委会"},{"id":"520623105210","text":"桃子园村委会"},{"id":"520623105211","text":"七寸坎村委会"},{"id":"520623105212","text":"尧寨村委会"},{"id":"520623105213","text":"地沟村委会"},{"id":"520623105214","text":"回龙村委会"},{"id":"520623105215","text":"新华村委会"},{"id":"520623105216","text":"仡来村委会"},{"id":"520623105217","text":"碧兴村委会"},{"id":"520623105218","text":"长兴村委会"},{"id":"520623105219","text":"地印村委会"},{"id":"520623105220","text":"李家园村委会"}]