[{"id":"522622102001","text":"兴隆街居民委员会"},{"id":"522622102203","text":"天堂村村民委员会"},{"id":"522622102206","text":"大井村村民委员会"},{"id":"522622102208","text":"代支村村民委员会"},{"id":"522622102211","text":"皎沙村村民委员会"},{"id":"522622102218","text":"黄猴村村民委员会"},{"id":"522622102219","text":"大石村村民委员会"},{"id":"522622102220","text":"榔木哨村村民委员会"},{"id":"522622102222","text":"岩头村村民委员会"},{"id":"522622102223","text":"金龙村村民委员会"},{"id":"522622102224","text":"石头堡村村民委员会"},{"id":"522622102226","text":"马场村村民委员会"},{"id":"522622102229","text":"下翁细村村民委员会"},{"id":"522622102230","text":"望坝村村民委员会"},{"id":"522622102231","text":"半山村村民委员会"},{"id":"522622102232","text":"塘都村村民委员会"},{"id":"522622102233","text":"重兴村村民委员会"},{"id":"522622102237","text":"上枫香村村民委员会"},{"id":"522622102240","text":"安江村村民委员会"},{"id":"522622102241","text":"黄金村村民委员会"},{"id":"522622102242","text":"五福村村民委员会"},{"id":"522622102243","text":"清水江村村民委员会"}]