[{"id":"445122116200","text":"径北村委会"},{"id":"445122116201","text":"下院村委会"},{"id":"445122116202","text":"英粉村委会"},{"id":"445122116203","text":"下广村委会"},{"id":"445122116204","text":"上广村委会"},{"id":"445122116205","text":"烈火村委会"},{"id":"445122116206","text":"龙光村委会"},{"id":"445122116207","text":"锡坑村委会"},{"id":"445122116208","text":"安溪村委会"},{"id":"445122116209","text":"新民村委会"},{"id":"445122116210","text":"刘厝埔村委会"},{"id":"445122116211","text":"内庵村委会"},{"id":"445122116212","text":"四罗村委会"},{"id":"445122116213","text":"乌溪村委会"},{"id":"445122116214","text":"魏厝楼村委会"},{"id":"445122116215","text":"厂埔村委会"},{"id":"445122116216","text":"军寮村委会"},{"id":"445122116217","text":"山斗村委会"},{"id":"445122116218","text":"青岚村委会"},{"id":"445122116219","text":"柘林村委会"},{"id":"445122116220","text":"月畔楼村民委员会"},{"id":"445122116500","text":"高蔡林场生活区"}]