[{"id":"410323100001","text":"西苑社区居民委员会"},{"id":"410323100002","text":"绿苑社区居民委员会"},{"id":"410323100003","text":"紫霞社区居民委员会"},{"id":"410323100004","text":"学林社区居民委员会"},{"id":"410323100005","text":"江庄社区居民委员会"},{"id":"410323100006","text":"暖泉社区居民委员会"},{"id":"410323100007","text":"马沟社区居民委员会"},{"id":"410323100008","text":"王庄社区居民委员会"},{"id":"410323100009","text":"大章社区居民委员会"},{"id":"410323100010","text":"西关社区居民委员会"},{"id":"410323100011","text":"东关社区居民委员会"},{"id":"410323100012","text":"河南社区居民委员会"},{"id":"410323100013","text":"北关社区居民委员会"},{"id":"410323100014","text":"鲍庄社区居民委员会"},{"id":"410323100015","text":"上河社区居民委员会"},{"id":"410323100016","text":"南庄社区居民委员会"},{"id":"410323100017","text":"寨湾社区居民委员会"},{"id":"410323100019","text":"陈湾社区居民委员会"},{"id":"410323100020","text":"宋村社区居民委员会"},{"id":"410323100021","text":"石庙社区居民委员会"},{"id":"410323100022","text":"塔地社区居民委员会"},{"id":"410323100023","text":"牌楼社区居民委员会"},{"id":"410323100024","text":"杨岭社区居民委员会"},{"id":"410323100025","text":"后峪社区居民委员会"},{"id":"410323100026","text":"何沟社区居民委员会"},{"id":"410323100217","text":"林庄村村民委员会"},{"id":"410323100218","text":"古路村村民委员会"},{"id":"410323100220","text":"上杨村村民委员会"},{"id":"410323100221","text":"王沟村村民委员会"},{"id":"410323100222","text":"西高村村民委员会"},{"id":"410323100223","text":"东高村村民委员会"},{"id":"410323100224","text":"尤坟咀村村民委员会"},{"id":"410323100225","text":"赵沟村村民委员会"},{"id":"410323100226","text":"安乐村村民委员会"},{"id":"410323100227","text":"刘村村民委员会"},{"id":"410323100228","text":"火虫驿村村民委员会"}]