[{"id":"410783110201","text":"佘西村委会"},{"id":"410783110202","text":"杨板城村委会"},{"id":"410783110203","text":"南王庄村委会"},{"id":"410783110204","text":"高店村委会"},{"id":"410783110205","text":"佘东村委会"},{"id":"410783110206","text":"朱口村委会"},{"id":"410783110207","text":"后佘村委会"},{"id":"410783110208","text":"钟家村委会"},{"id":"410783110209","text":"北关村委会"},{"id":"410783110210","text":"苗找寨村委会"},{"id":"410783110211","text":"武找寨村委会"},{"id":"410783110212","text":"南关村委会"},{"id":"410783110213","text":"东张弓寨村委会"},{"id":"410783110214","text":"牛庄村委会"},{"id":"410783110215","text":"西郝家村委会"},{"id":"410783110216","text":"佘南村委会"},{"id":"410783110217","text":"赵家村委会"},{"id":"410783110218","text":"西黄找寨村委会"},{"id":"410783110219","text":"东黄找寨村委会"},{"id":"410783110220","text":"葛寨村委会"},{"id":"410783110221","text":"前楼村委会"},{"id":"410783110222","text":"东邵二寨村委会"},{"id":"410783110223","text":"河里高村委会"},{"id":"410783110224","text":"北邵二寨村委会"},{"id":"410783110225","text":"车寨村委会"},{"id":"410783110226","text":"魁王庄村委会"},{"id":"410783110227","text":"邵二寨村委会"},{"id":"410783110228","text":"陈庄村委会"},{"id":"410783110229","text":"王岸下村委会"},{"id":"410783110230","text":"东连庄村委会"},{"id":"410783110231","text":"佘新庄村委会"},{"id":"410783110232","text":"翟家村委会"},{"id":"410783110233","text":"高岸下村委会"},{"id":"410783110234","text":"郭岸下村委会"},{"id":"410783110235","text":"西连庄村委会"},{"id":"410783110236","text":"金岸下村委会"},{"id":"410783110237","text":"西韩板城村委会"},{"id":"410783110238","text":"寺门村委会"},{"id":"410783110239","text":"太平庄村委会"},{"id":"410783110240","text":"西邵二寨村委会"},{"id":"410783110241","text":"东关村委会"},{"id":"410783110242","text":"新起寨村委会"},{"id":"410783110243","text":"西张弓寨村委会"},{"id":"410783110244","text":"黄庄村委会"},{"id":"410783110245","text":"西庄村委会"},{"id":"410783110246","text":"韩板城村委会"},{"id":"410783110247","text":"陈板城村委会"},{"id":"410783110248","text":"东郝家村委会"},{"id":"410783110249","text":"南寨村委会"}]