[{"id":"410882201200","text":"东祝策村委会"},{"id":"410882201201","text":"西祝策村委会"},{"id":"410882201202","text":"前庄村委会"},{"id":"410882201203","text":"索庄村委会"},{"id":"410882201204","text":"段庄村委会"},{"id":"410882201205","text":"李大人庄村委会"},{"id":"410882201206","text":"南李庄村委会"},{"id":"410882201207","text":"南住村委会"},{"id":"410882201208","text":"北住村委会"},{"id":"410882201209","text":"大辛王村委会"},{"id":"410882201210","text":"小辛王村委会"},{"id":"410882201211","text":"王庄村委会"},{"id":"410882201213","text":"东申召村委会"},{"id":"410882201214","text":"西申召村委会"},{"id":"410882201215","text":"赵庄村委会"},{"id":"410882201216","text":"仲贤村委会"},{"id":"410882201217","text":"西王召村委会"},{"id":"410882201218","text":"东王召村委会"},{"id":"410882201219","text":"马铺村委会"},{"id":"410882201220","text":"冯翊村委会"},{"id":"410882201221","text":"龙涧村委会"},{"id":"410882201222","text":"言状村委会"},{"id":"410882201223","text":"卫庄村委会"},{"id":"410882201224","text":"尚香村委会"},{"id":"410882201225","text":"言庄村委会"},{"id":"410882201226","text":"彭城村委会"},{"id":"410882201227","text":"前兴福村委会"},{"id":"410882201228","text":"后兴福村委会"},{"id":"410882201229","text":"木楼村委会"},{"id":"410882201230","text":"东木楼村委会"},{"id":"410882201231","text":"西木楼村委会"},{"id":"410882201232","text":"张庄村委会"},{"id":"410882201233","text":"陈庄村委会"},{"id":"410882201234","text":"感化村委会"},{"id":"410882201235","text":"南荒村委会"},{"id":"410882201236","text":"东苟庄村委会"},{"id":"410882201237","text":"苟庄屯村委会"},{"id":"410882201238","text":"邢庄村委会"},{"id":"410882201239","text":"西里村委会"},{"id":"410882201240","text":"东里村委会"},{"id":"410882201241","text":"土培村委会"},{"id":"410882201242","text":"北龙盘村委会"},{"id":"410882201243","text":"南龙盘村委会"},{"id":"410882201244","text":"冷庄村委会"},{"id":"410882201245","text":"东贾村委会"},{"id":"410882201246","text":"西贾村委会"}]