[{"id":"411327101200","text":"桥头街村民委员会"},{"id":"411327101201","text":"许庄村民委员会"},{"id":"411327101202","text":"小河流村民委员会"},{"id":"411327101203","text":"史庄村民委员会"},{"id":"411327101204","text":"陶庄村民委员会"},{"id":"411327101205","text":"范朱刘村民委员会"},{"id":"411327101206","text":"相庄村民委员会"},{"id":"411327101207","text":"何营村民委员会"},{"id":"411327101208","text":"姚营村民委员会"},{"id":"411327101209","text":"泥河村民委员会"},{"id":"411327101210","text":"老庄村民委员会"},{"id":"411327101211","text":"明章村民委员会"},{"id":"411327101212","text":"王蛮村民委员会"},{"id":"411327101213","text":"王坊村民委员会"},{"id":"411327101214","text":"吴氏营村民委员会"},{"id":"411327101215","text":"新街村民委员会"},{"id":"411327101216","text":"马蹬村民委员会"},{"id":"411327101217","text":"石桥村民委员会"}]