[{"id":"411403004001","text":"三和社区"},{"id":"411403004003","text":"雪苑社区"},{"id":"411403004004","text":"府前社区"},{"id":"411403004005","text":"丰源居委会"},{"id":"411403004006","text":"北海社区"},{"id":"411403004007","text":"新华居委会"},{"id":"411403004008","text":"花园居委会"},{"id":"411403004009","text":"三商社区"},{"id":"411403004010","text":"夏营社区"},{"id":"411403004011","text":"宇航居委会"},{"id":"411403004012","text":"金世纪居委会"},{"id":"411403004013","text":"银河居委会"},{"id":"411403004014","text":"长江居委会"},{"id":"411403004015","text":"天河居委会"},{"id":"411403004016","text":"鑫源居委会"},{"id":"411403004017","text":"武宅社区"},{"id":"411403004018","text":"奥园居委会"},{"id":"411403004019","text":"九州居委会"},{"id":"411403004020","text":"紫荆社区"}]