[{"id":"411481125201","text":"李楼村委会"},{"id":"411481125202","text":"前堤湾村委会"},{"id":"411481125203","text":"种寨村委会"},{"id":"411481125204","text":"邵山村委会"},{"id":"411481125205","text":"郭集村委会"},{"id":"411481125206","text":"排集村委会"},{"id":"411481125207","text":"贾洼村委会"},{"id":"411481125208","text":"南鱼山村委会"},{"id":"411481125209","text":"条河村委会"},{"id":"411481125210","text":"李双楼村委会"},{"id":"411481125211","text":"徐山村委会"},{"id":"411481125212","text":"翟营村委会"},{"id":"411481125213","text":"宗楼村委会"},{"id":"411481125214","text":"王山村委会"},{"id":"411481125215","text":"李各村委会"},{"id":"411481125216","text":"邸楼村委会"},{"id":"411481125217","text":"吴营村委会"},{"id":"411481125218","text":"王石庄村委会"},{"id":"411481125219","text":"祝庄村委会"},{"id":"411481125220","text":"郑楼村委会"},{"id":"411481125221","text":"冯庄村委会"},{"id":"411481125222","text":"水库村委会"},{"id":"411481125223","text":"东候庙村委会"},{"id":"411481125224","text":"侯庵村委会"},{"id":"411481125225","text":"王庙村委会"},{"id":"411481125226","text":"肖庄村委会"},{"id":"411481125227","text":"北鱼山村委会"},{"id":"411481125228","text":"后堤湾村委会"},{"id":"411481125229","text":"西侯庙村委会"},{"id":"411481125230","text":"潘道口村委会"}]