[{"id":"411524104201","text":"汪桥村委会"},{"id":"411524104202","text":"鲍楼村委会"},{"id":"411524104203","text":"肖坳村委会"},{"id":"411524104204","text":"墩塘村委会"},{"id":"411524104205","text":"钟铺村委会"},{"id":"411524104206","text":"河铺村委会"},{"id":"411524104207","text":"土庙村委会"},{"id":"411524104208","text":"孔楼村委会"},{"id":"411524104209","text":"邱湾村委会"},{"id":"411524104210","text":"丁坳村委会"},{"id":"411524104211","text":"邓家村委会"},{"id":"411524104212","text":"秦湾村委会"},{"id":"411524104213","text":"汪楼村委会"},{"id":"411524104214","text":"董畈村委会"},{"id":"411524104215","text":"铜山村委会"},{"id":"411524104216","text":"曹畈村委会"},{"id":"411524104217","text":"天井村委会"},{"id":"411524104218","text":"古岗村委会"},{"id":"411524104219","text":"东庙村委会"},{"id":"411524104220","text":"六营村委会"},{"id":"411524104221","text":"双桥村委会"},{"id":"411524104222","text":"万河村委会"},{"id":"411524104223","text":"邱庄村委会"},{"id":"411524104224","text":"黄岗村委会"},{"id":"411524104225","text":"潘湾村委会"}]