[{"id":"220113006001","text":"苇子沟居委会"},{"id":"220113006200","text":"杨家烧锅村委会"},{"id":"220113006201","text":"庙沟村委会"},{"id":"220113006202","text":"西地村委会"},{"id":"220113006203","text":"头道咀子村委会"},{"id":"220113006204","text":"双桥子村委会"},{"id":"220113006205","text":"小苇子沟村委会"},{"id":"220113006206","text":"拉拉屯村委会"},{"id":"220113006207","text":"石头咀子村委会"},{"id":"220113006208","text":"二道林子村委会"},{"id":"220113006209","text":"官地村委会"},{"id":"220113006210","text":"靠山村委会"},{"id":"220113006211","text":"大苇子沟村委会"},{"id":"220113006212","text":"大院村委会"},{"id":"220113006213","text":"新开村委会"},{"id":"220113006214","text":"庆阳村委会"},{"id":"220113006215","text":"月明楼村委会"},{"id":"220113006216","text":"双兴村委会"},{"id":"220113006217","text":"梨树村委会"},{"id":"220113006218","text":"八台村委会"},{"id":"220113006219","text":"四合村委会"},{"id":"220113006220","text":"卧龙泉村委会"},{"id":"220113006221","text":"西山村委会"},{"id":"220113006222","text":"胜利村委会"},{"id":"220113006223","text":"兴隆沟村委会"},{"id":"220113006224","text":"东兴村委会"},{"id":"220113006225","text":"富民村委会"}]