[{"id":"330327122004","text":"合作社区"},{"id":"330327122200","text":"南茶寮村委会"},{"id":"330327122201","text":"北岙村委会"},{"id":"330327122203","text":"北茶寮村委会"},{"id":"330327122208","text":"乌石岭村委会"},{"id":"330327122210","text":"六板桥村委会"},{"id":"330327122212","text":"马鞍村委会"},{"id":"330327122214","text":"罗厝村委会"},{"id":"330327122216","text":"溪头埠村委会"},{"id":"330327122217","text":"祺临村委会"},{"id":"330327122219","text":"雅儒村委会"},{"id":"330327122221","text":"护法寺村委会"},{"id":"330327122223","text":"神山村委会"},{"id":"330327122224","text":"新庄村委会"},{"id":"330327122225","text":"宫兴村委会"}]