[{"id":"330683100001","text":"甘霖居委会"},{"id":"330683100002","text":"博济居委会"},{"id":"330683100200","text":"雅沈村委会"},{"id":"330683100201","text":"尹家村委会"},{"id":"330683100202","text":"黄胜堂村委会"},{"id":"330683100203","text":"大砩口村委会"},{"id":"330683100204","text":"姜王村委会"},{"id":"330683100205","text":"桃源村委会"},{"id":"330683100206","text":"甘三村委会"},{"id":"330683100207","text":"甘霖新村委会"},{"id":"330683100208","text":"甘一村委会"},{"id":"330683100209","text":"士明村委会"},{"id":"330683100210","text":"俞赵村委会"},{"id":"330683100211","text":"西湖头村委会"},{"id":"330683100212","text":"后袁湖村委会"},{"id":"330683100213","text":"蛟镇村委会"},{"id":"330683100214","text":"黄塘岭村委会"},{"id":"330683100215","text":"东山村委会"},{"id":"330683100216","text":"东王村委会"},{"id":"330683100217","text":"黄箭坂村委会"},{"id":"330683100218","text":"上高村委会"},{"id":"330683100219","text":"柳岸村委会"},{"id":"330683100220","text":"白泥墩村委会"},{"id":"330683100221","text":"孙屋村委会"},{"id":"330683100222","text":"桂山村委会"},{"id":"330683100223","text":"东雅后俞村委会"},{"id":"330683100224","text":"西叶村委会"},{"id":"330683100225","text":"江田村委会"},{"id":"330683100226","text":"福宅安村委会"},{"id":"330683100227","text":"甲秀坂村委会"},{"id":"330683100228","text":"雅言楼村委会"},{"id":"330683100229","text":"官珏村委会"},{"id":"330683100230","text":"查村村委会"},{"id":"330683100231","text":"马塘村委会"},{"id":"330683100232","text":"求家坎村委会"},{"id":"330683100233","text":"前后朱村委会"},{"id":"330683100234","text":"东湖村委会"},{"id":"330683100235","text":"义杜村委会"},{"id":"330683100236","text":"过祝山村委会"},{"id":"330683100237","text":"笆前西村委会"},{"id":"330683100238","text":"下洋村委会"},{"id":"330683100239","text":"大王庙村委会"},{"id":"330683100240","text":"前王村委会"},{"id":"330683100241","text":"上蔡村委会"},{"id":"330683100242","text":"下蔡村委会"},{"id":"330683100243","text":"上路西村委会"},{"id":"330683100244","text":"下路西村委会"},{"id":"330683100245","text":"东张村委会"},{"id":"330683100246","text":"西叶家村委会"},{"id":"330683100247","text":"上朱村委会"},{"id":"330683100248","text":"罗村村委会"},{"id":"330683100249","text":"湖坊村委会"},{"id":"330683100250","text":"郑庄村委会"},{"id":"330683100251","text":"楼下村委会"},{"id":"330683100252","text":"上沙地村委会"},{"id":"330683100253","text":"下沙地村委会"},{"id":"330683100254","text":"后史村委会"},{"id":"330683100255","text":"孔村村委会"},{"id":"330683100256","text":"上塘头村委会"},{"id":"330683100257","text":"大王田湾村委会"},{"id":"330683100258","text":"苍岩村委会"},{"id":"330683100259","text":"丽湖村委会"},{"id":"330683100260","text":"殿前村委会"},{"id":"330683100261","text":"施家岙村委会"},{"id":"330683100262","text":"和尚田村委会"},{"id":"330683100263","text":"田东村委会"},{"id":"330683100264","text":"长安村委会"},{"id":"330683100265","text":"石坪村委会"},{"id":"330683100266","text":"大小坑村委会"},{"id":"330683100267","text":"大岩坂村委会"},{"id":"330683100268","text":"石道地村委会"},{"id":"330683100269","text":"求杓湾村委会"},{"id":"330683100270","text":"毫岭村委会"}]