[{"id":"420882111001","text":"永漋街社区居委会"},{"id":"420882111002","text":"杨浲街社区居委会"},{"id":"420882111200","text":"同益村委会"},{"id":"420882111201","text":"青龙庵村委会"},{"id":"420882111202","text":"青年村委会"},{"id":"420882111203","text":"张家岭村委会"},{"id":"420882111204","text":"满天星村委会"},{"id":"420882111205","text":"卢相台村委会"},{"id":"420882111206","text":"公益村委会"},{"id":"420882111207","text":"张常台村委会"},{"id":"420882111208","text":"红旗村委会"},{"id":"420882111209","text":"贾家台村委会"},{"id":"420882111210","text":"刘家榨村委会"},{"id":"420882111211","text":"群力村委会"},{"id":"420882111212","text":"石板巷村委会"},{"id":"420882111213","text":"曾口村委会"},{"id":"420882111214","text":"陶家岭村委会"},{"id":"420882111215","text":"马家岭村委会"},{"id":"420882111216","text":"石女山村委会"},{"id":"420882111217","text":"古城口村委会"},{"id":"420882111218","text":"杨家浲村委会"},{"id":"420882111219","text":"黎家大岭村委会"},{"id":"420882111220","text":"高湖街村委会"},{"id":"420882111221","text":"黎家垸村委会"},{"id":"420882111222","text":"绿化村委会"},{"id":"420882111223","text":"上陈桥村委会"},{"id":"420882111224","text":"红光村委会"},{"id":"420882111225","text":"新河口村委会"},{"id":"420882111226","text":"樊家巷村委会"},{"id":"420882111227","text":"下陈桥村委会"},{"id":"420882111228","text":"严家墩村委会"},{"id":"420882111229","text":"聂畈村委会"}]