[{"id":"421083108001","text":"戴市社区居委会"},{"id":"421083108200","text":"榨台村村民委员会"},{"id":"421083108201","text":"关圣庙村村民委员会"},{"id":"421083108202","text":"河坝村村民委员会"},{"id":"421083108203","text":"南林村村民委员会"},{"id":"421083108204","text":"沈庙村村民委员会"},{"id":"421083108205","text":"绍南村村民委员会"},{"id":"421083108206","text":"水塌埠村村民委员会"},{"id":"421083108207","text":"寄木塌村村民委员会"},{"id":"421083108208","text":"树桩河村村民委员会"},{"id":"421083108211","text":"竹林村村民委员会"},{"id":"421083108212","text":"百桥村村民委员会"},{"id":"421083108213","text":"螺滩村村民委员会"},{"id":"421083108214","text":"官港河村村民委员会"},{"id":"421083108215","text":"卢墩村村民委员会"},{"id":"421083108216","text":"柴林村村民委员会"},{"id":"421083108217","text":"秦口村村民委员会"},{"id":"421083108219","text":"戴家场村村民委员会"},{"id":"421083108220","text":"戴剅沟村村民委员会"},{"id":"421083108221","text":"沙洋河村村民委员会"},{"id":"421083108500","text":"潭湖渔场生活区"}]