[{"id":"150421204200","text":"特尼格尔嘎查村"},{"id":"150421204201","text":"毛盖图嘎查村"},{"id":"150421204202","text":"达兰花嘎查村"},{"id":"150421204203","text":"石桌子嘎查村"},{"id":"150421204204","text":"上新打井嘎查村"},{"id":"150421204205","text":"道日新呼都格嘎查村"},{"id":"150421204206","text":"萨如拉塔拉嘎查村"},{"id":"150421204207","text":"合作村民委员会"},{"id":"150421204208","text":"准迫毛都村民委员会"},{"id":"150421204209","text":"达日罕村民委员会"},{"id":"150421204210","text":"新发村民委员会"},{"id":"150421204211","text":"十间房村民委员会"},{"id":"150421204212","text":"南图古日格嘎查村"},{"id":"150421204213","text":"巴润诺尔嘎查村"},{"id":"150421204214","text":"通希嘎查村"},{"id":"150421204215","text":"敦达诺尔嘎查村"},{"id":"150421204216","text":"准诺尔嘎查村"}]