[{"id":"150523108200","text":"吉日嘎郎吐嘎查"},{"id":"150523108201","text":"巴仁仓嘎查"},{"id":"150523108202","text":"新艾力嘎查"},{"id":"150523108203","text":"永丰村委会"},{"id":"150523108204","text":"四合福村委会"},{"id":"150523108205","text":"孟家屯村委会"},{"id":"150523108206","text":"福厚村委会"},{"id":"150523108207","text":"新风村委会"},{"id":"150523108208","text":"辽富村委会"},{"id":"150523108209","text":"保合村委会"},{"id":"150523108210","text":"保发村委会"},{"id":"150523108211","text":"路北营子村委会"},{"id":"150523108212","text":"保安村委会"},{"id":"150523108213","text":"哈日虎硕村委会"},{"id":"150523108214","text":"敖包筒嘎查"},{"id":"150523108500","text":"保安林场"}]