[{"id":"120119115201","text":"西王唐村委会"},{"id":"120119115202","text":"李四庄村委会"},{"id":"120119115203","text":"肖河庄村委会"},{"id":"120119115204","text":"小王庄村委会"},{"id":"120119115205","text":"大王庄村委会"},{"id":"120119115206","text":"薄庄子村委会"},{"id":"120119115207","text":"魏良庄村委会"},{"id":"120119115208","text":"傅庄子村委会"},{"id":"120119115209","text":"东王唐村委会"},{"id":"120119115210","text":"中周庄村委会"},{"id":"120119115211","text":"玉润庄村委会"},{"id":"120119115212","text":"柳林村委会"},{"id":"120119115213","text":"大潘庄村委会"},{"id":"120119115214","text":"韩庄子村委会"},{"id":"120119115215","text":"南小屯村委会"},{"id":"120119115216","text":"西桥头村委会"},{"id":"120119115217","text":"韩刘庄村委会"},{"id":"120119115218","text":"高庄子村委会"},{"id":"120119115219","text":"林庄户村委会"},{"id":"120119115220","text":"其林庄村委会"},{"id":"120119115221","text":"南齐庄村委会"},{"id":"120119115222","text":"许有庄村委会"},{"id":"120119115223","text":"铺户庄村委会"},{"id":"120119115224","text":"于庄户村委会"},{"id":"120119115225","text":"西孔庄村委会"},{"id":"120119115226","text":"王家堡村委会"},{"id":"120119115227","text":"侯三八村委会"},{"id":"120119115228","text":"南周庄村委会"},{"id":"120119115229","text":"张庄子村委会"},{"id":"120119115230","text":"栗庄子村委会"},{"id":"120119115231","text":"宗家庄村委会"},{"id":"120119115232","text":"南富家屯村委会"},{"id":"120119115233","text":"娘娘庙村委会"},{"id":"120119115234","text":"老宋庄村委会"},{"id":"120119115235","text":"打鱼庄村委会"},{"id":"120119115236","text":"崔辛庄村委会"},{"id":"120119115237","text":"南三岔口村委会"},{"id":"120119115238","text":"王大郎村委会"},{"id":"120119115239","text":"秦家庄村委会"},{"id":"120119115240","text":"老丁庄村委会"},{"id":"120119115241","text":"祥福庄村委会"},{"id":"120119115242","text":"丁辛庄村委会"},{"id":"120119115243","text":"邵庄子村委会"}]