[{"id":"130581001","text":"凤岗街道办事处"},{"id":"130581002","text":"南杜街道办事处"},{"id":"130581003","text":"北胡街道办事处"},{"id":"130581004","text":"西丁街道办事处"},{"id":"130581100","text":"苏村镇"},{"id":"130581101","text":"大高村镇"},{"id":"130581102","text":"垂杨镇"},{"id":"130581103","text":"明化镇"},{"id":"130581104","text":"段芦头镇"},{"id":"130581105","text":"紫冢镇"},{"id":"130581200","text":"大村乡"},{"id":"130581201","text":"南便村乡"},{"id":"130581202","text":"大屯乡"},{"id":"130581203","text":"王道寨乡"},{"id":"130581204","text":"薛吴村乡"}]