[{"id":"140522104200","text":"刘东村委会"},{"id":"140522104201","text":"刘西村委会"},{"id":"140522104202","text":"槐树腰村委会"},{"id":"140522104203","text":"南上村委会"},{"id":"140522104204","text":"芹池村委会"},{"id":"140522104205","text":"川河村委会"},{"id":"140522104206","text":"游仙村委会"},{"id":"140522104207","text":"候甲村委会"},{"id":"140522104208","text":"吕河村委会"},{"id":"140522104209","text":"大峪沟村委会"},{"id":"140522104210","text":"武甲村委会"},{"id":"140522104211","text":"阳陵村委会"},{"id":"140522104212","text":"宜壁村委会"},{"id":"140522104213","text":"吕庄村委会"},{"id":"140522104214","text":"北宜固村委会"},{"id":"140522104215","text":"南宜固村委会"},{"id":"140522104216","text":"马庄村委会"},{"id":"140522104217","text":"大壑村委会"},{"id":"140522104218","text":"羊泉村委会"},{"id":"140522104219","text":"庙坡村委会"},{"id":"140522104220","text":"油坊头村委会"},{"id":"140522104221","text":"贾寨村委会"},{"id":"140522104222","text":"原庄村委会"},{"id":"140522104223","text":"柴庄村委会"},{"id":"140522104224","text":"伯附村委会"},{"id":"140522104225","text":"大西沟村委会"},{"id":"140522104226","text":"小西沟村委会"}]