[{"id":"140829105200","text":"将窝村委会"},{"id":"140829105201","text":"禹庙村委会"},{"id":"140829105202","text":"三门村委会"},{"id":"140829105203","text":"大咀村委会"},{"id":"140829105204","text":"过村村委会"},{"id":"140829105205","text":"东马村委会"},{"id":"140829105206","text":"淹底村委会"},{"id":"140829105207","text":"东中村委会"},{"id":"140829105208","text":"狮沟村委会"},{"id":"140829105209","text":"寨后村委会"},{"id":"140829105210","text":"岳家庄村委会"},{"id":"140829105211","text":"刘家庄村委会"},{"id":"140829105212","text":"徐滹沱村委会"},{"id":"140829105213","text":"望原村委会"}]