[{"id":"150429104200","text":"大营子村民委员会"},{"id":"150429104201","text":"下拐村民委员会"},{"id":"150429104202","text":"八沟道村民委员会"},{"id":"150429104203","text":"上拐村民委员会"},{"id":"150429104204","text":"南毛扎子村民委员会"},{"id":"150429104205","text":"北毛扎子村民委员会"},{"id":"150429104206","text":"山神庙子村民委员会"},{"id":"150429104207","text":"三道河子村民委员会"},{"id":"150429104208","text":"四道沟村民委员会"},{"id":"150429104209","text":"兴家营子村民委员会"},{"id":"150429104210","text":"二道梁村民委员会"},{"id":"150429104211","text":"西泉村民委员会"},{"id":"150429104212","text":"打鹿沟门村民委员会"},{"id":"150429104213","text":"东打鹿沟村民委员会"},{"id":"150429104214","text":"西打鹿沟村民委员会"},{"id":"150429104215","text":"乌梁苏村民委员会"},{"id":"150429104216","text":"长青村民委员会"},{"id":"150429104217","text":"盆底沟村民委员会"},{"id":"150429104218","text":"范杖子村民委员会"},{"id":"150429104219","text":"哈拉宝沟村民委员会"},{"id":"150429104220","text":"打虎石村民委员会"},{"id":"150429104221","text":"朝阳沟村民委员会"}]