[{"id":"230421101001","text":"第一居委会"},{"id":"230421101002","text":"第二居委会"},{"id":"230421101003","text":"第三居委会"},{"id":"230421101004","text":"第四居委会"},{"id":"230421101005","text":"第五居委会"},{"id":"230421101200","text":"奋斗村村委会"},{"id":"230421101201","text":"双胜村村委会"},{"id":"230421101202","text":"九里庄村村委会"},{"id":"230421101203","text":"森山村村委会"},{"id":"230421101204","text":"新鹤村村委会"},{"id":"230421101205","text":"常胜村村委会"},{"id":"230421101206","text":"振兴村村委会"},{"id":"230421101207","text":"金山村村委会"},{"id":"230421101208","text":"云山合村村委会"},{"id":"230421101209","text":"三双村村委会"}]