[{"id":"330723103200","text":"泉二村委会"},{"id":"330723103201","text":"山方村委会"},{"id":"330723103202","text":"白革村委会"},{"id":"330723103203","text":"泉三村委会"},{"id":"330723103204","text":"丁塘背村委会"},{"id":"330723103205","text":"麻田村委会"},{"id":"330723103206","text":"阳丰村委会"},{"id":"330723103207","text":"官田村委会"},{"id":"330723103208","text":"瑶村村委会"},{"id":"330723103209","text":"大塘口村委会"},{"id":"330723103210","text":"王山头村委会"},{"id":"330723103211","text":"盛岭下村委会"},{"id":"330723103212","text":"宅园村委会"},{"id":"330723103213","text":"王毛山村委会"},{"id":"330723103214","text":"夏嘉畈村委会"},{"id":"330723103215","text":"江山村委会"},{"id":"330723103216","text":"刘宅村委会"},{"id":"330723103217","text":"里念坑村委会"},{"id":"330723103218","text":"湖沿村委会"},{"id":"330723103219","text":"石甲口村委会"},{"id":"330723103220","text":"黄坛村委会"},{"id":"330723103221","text":"上滩村委会"},{"id":"330723103222","text":"杨村村委会"},{"id":"330723103223","text":"丰溪村委会"},{"id":"330723103224","text":"麻蓬村委会"},{"id":"330723103225","text":"车苏村委会"},{"id":"330723103226","text":"董源坑村委会"},{"id":"330723103227","text":"下宅口村委会"},{"id":"330723103228","text":"西陈村委会"},{"id":"330723103229","text":"黄长岗村委会"},{"id":"330723103230","text":"巩宅村委会"},{"id":"330723103231","text":"茆角村委会"},{"id":"330723103232","text":"大王岭村委会"},{"id":"330723103233","text":"清源村委会"},{"id":"330723103234","text":"姆山前村委会"},{"id":"330723103235","text":"西项村委会"},{"id":"330723103236","text":"王元村委会"},{"id":"330723103237","text":"郑宅村委会"},{"id":"330723103238","text":"仓部堰村委会"},{"id":"330723103239","text":"新屋村委会"},{"id":"330723103240","text":"珠门村委会"},{"id":"330723103241","text":"叶墙头村委会"},{"id":"330723103242","text":"项店村委会"},{"id":"330723103243","text":"张宅村委会"},{"id":"330723103244","text":"兰芝村委会"},{"id":"330723103245","text":"客塘村委会"},{"id":"330723103246","text":"清溪村委会"}]