[{"id":"360111001000","text":"青山路街道办事处"},{"id":"360111003000","text":"上海路街道办事处"},{"id":"360111004000","text":"南钢街道办事处"},{"id":"360111005000","text":"站东街道办事处"},{"id":"360111100000","text":"京东镇"},{"id":"360111103000","text":"罗家镇"},{"id":"360111104000","text":"湖坊镇"},{"id":"360111105000","text":"塘山镇"},{"id":"360111180000","text":"蛟桥镇（南昌经济技术开发区）"},{"id":"360111400000","text":"南昌昌东工业区"},{"id":"360111481000","text":"白水湖管理处（南昌经济技术开发区）"},{"id":"360111482000","text":"冠山管理处（南昌经济技术开发区）"},{"id":"360111490000","text":"艾溪湖管理处（南昌高新开发区）"},{"id":"360111493000","text":"湖西新建区（南昌高新开发区）"}]