[{"id":"371321101001","text":"岸堤社区居委会"},{"id":"371321101207","text":"局埠村委会"},{"id":"371321101208","text":"小峪庄村委会"},{"id":"371321101209","text":"西坡池村委会"},{"id":"371321101219","text":"大峪庄村委会"},{"id":"371321101222","text":"田家北村委会"},{"id":"371321101223","text":"梁家北村委会"},{"id":"371321101224","text":"东北村委会"},{"id":"371321101225","text":"红光村委会"},{"id":"371321101226","text":"新兴村委会"},{"id":"371321101228","text":"李家庄子村委会"},{"id":"371321101229","text":"塘子村委会"},{"id":"371321101231","text":"唐家峪子村委会"},{"id":"371321101237","text":"艾山东村委会"},{"id":"371321101241","text":"仁合庄村委会"},{"id":"371321101242","text":"河子沟村委会"},{"id":"371321101246","text":"冯家庄村委会"},{"id":"371321101247","text":"柳行岔村委会"},{"id":"371321101249","text":"兴旺庄村委会"},{"id":"371321101250","text":"西岩路村委会"},{"id":"371321101273","text":"杏山子村委会"},{"id":"371321101274","text":"罗圈峪村委会"},{"id":"371321101276","text":"池畔村委会"},{"id":"371321101284","text":"蔡家峪子村委会"},{"id":"371321101285","text":"大新庄村委会"},{"id":"371321101286","text":"董家峪子村委会"},{"id":"371321101287","text":"合兴村委会"},{"id":"371321101288","text":"库东村委会"},{"id":"371321101289","text":"前高湖村委会"},{"id":"371321101290","text":"万佛山村委会"},{"id":"371321101291","text":"王山峪村委会"},{"id":"371321101292","text":"岩路村村委会"},{"id":"371321101293","text":"中高湖村委会"},{"id":"371321101294","text":"玉泉庄村委会"},{"id":"371321101295","text":"上高湖村委会"}]