[{"id":"410103001000","text":"淮河路街道办事处"},{"id":"410103002000","text":"解放路街道办事处"},{"id":"410103003000","text":"铭功路街道办事处"},{"id":"410103004000","text":"一马路街道办事处"},{"id":"410103005000","text":"蜜蜂张街道办事处"},{"id":"410103006000","text":"五里堡街道办事处"},{"id":"410103007000","text":"大学路街道办事处"},{"id":"410103008000","text":"建中街街道办事处"},{"id":"410103009000","text":"福华街街道办事处"},{"id":"410103010000","text":"德化街街道办事处"},{"id":"410103011000","text":"嵩山路街道办事处"},{"id":"410103012000","text":"京广路街道办事处"},{"id":"410103013000","text":"长江路街道办事处"},{"id":"410103015000","text":"人和路街道办事处"},{"id":"410103100000","text":"马寨镇"},{"id":"410103201000","text":"侯寨乡"}]