[{"id":"410782208201","text":"沙窑村委会"},{"id":"410782208202","text":"水寨窑村委会"},{"id":"410782208203","text":"南窑村委会"},{"id":"410782208204","text":"北沙水村委会"},{"id":"410782208205","text":"南沙水村委会"},{"id":"410782208206","text":"中腊江村委会"},{"id":"410782208207","text":"水磨村委会"},{"id":"410782208208","text":"南坪村委会"},{"id":"410782208209","text":"郭亮村委会"},{"id":"410782208210","text":"井郊村委会"},{"id":"410782208211","text":"岭西村委会"},{"id":"410782208212","text":"石门郊村委会"},{"id":"410782208213","text":"涧顶村委会"},{"id":"410782208214","text":"后庄村委会"},{"id":"410782208215","text":"新庄村委会"},{"id":"410782208216","text":"白庙村委会"},{"id":"410782208217","text":"小井村委会"},{"id":"410782208218","text":"金牛寺村委会"}]