[{"id":"411426208201","text":"孟大桥村委会"},{"id":"411426208202","text":"五里桥村委会"},{"id":"411426208203","text":"朱路口村委会"},{"id":"411426208204","text":"梅林村委会"},{"id":"411426208205","text":"何土楼村委会"},{"id":"411426208206","text":"杨井村委会"},{"id":"411426208207","text":"汤庄村委会"},{"id":"411426208208","text":"祝楼村委会"},{"id":"411426208209","text":"三里村委会"},{"id":"411426208210","text":"胶刘庄村委会"},{"id":"411426208211","text":"宋营村委会"},{"id":"411426208212","text":"何营村委会"},{"id":"411426208213","text":"何套楼村委会"},{"id":"411426208214","text":"丁瓦房村委会"},{"id":"411426208215","text":"孙庄寨村委会"},{"id":"411426208216","text":"孙六湾村委会"},{"id":"411426208217","text":"王营村委会"},{"id":"411426208218","text":"柴庄村委会"},{"id":"411426208219","text":"张庄村委会"},{"id":"411426208220","text":"高台子王庄村委会"},{"id":"411426208221","text":"大尹村委会"},{"id":"411426208222","text":"槐刘村委会"},{"id":"411426208223","text":"苗李庄村委会"},{"id":"411426208224","text":"前刘村委会"}]