[{"id":"420682104001","text":"仙人渡居委会"},{"id":"420682104002","text":"西街居委会"},{"id":"420682104200","text":"南岗村委会"},{"id":"420682104201","text":"黄家庄村委会"},{"id":"420682104202","text":"黄家营村委会"},{"id":"420682104203","text":"刘家营村委会"},{"id":"420682104204","text":"王家营村委会"},{"id":"420682104205","text":"范家湾村委会"},{"id":"420682104206","text":"莫家营村委会"},{"id":"420682104207","text":"崔家营村委会"},{"id":"420682104208","text":"辛庙村委会"},{"id":"420682104209","text":"白鹤岗村委会"},{"id":"420682104210","text":"钟家寨村委会"},{"id":"420682104211","text":"龙王冲村委会"},{"id":"420682104212","text":"范家营村委会"},{"id":"420682104213","text":"马家冲村委会"},{"id":"420682104214","text":"林岗村委会"},{"id":"420682104215","text":"柴店岗村委会"},{"id":"420682104216","text":"杜家河村委会"},{"id":"420682104217","text":"北沟村委会"},{"id":"420682104218","text":"安家岗村委会"},{"id":"420682104219","text":"邓家营村委会"},{"id":"420682104220","text":"靳家湾村委会"},{"id":"420682104222","text":"西张湾村委会"},{"id":"420682104223","text":"茹家湾村委会"},{"id":"420682104224","text":"李家染房村委会"},{"id":"420682104225","text":"张岗村委会"},{"id":"420682104226","text":"张家竹园村委会"},{"id":"420682104227","text":"大张营村委会"},{"id":"420682104228","text":"王家楼村委会"},{"id":"420682104229","text":"马家岗村委会"},{"id":"420682104230","text":"雷家牌坊村委会"},{"id":"420682104231","text":"小张营村委会"}]