[{"id":"420881103001","text":"胡集社区居委会"},{"id":"420881103002","text":"桥垱社区居委会"},{"id":"420881103003","text":"金山社区居委会"},{"id":"420881103004","text":"转斗社区居委会"},{"id":"420881103005","text":"放马山社区居委会"},{"id":"420881103006","text":"王集社区居委会"},{"id":"420881103007","text":"大峪口社区居委会"},{"id":"420881103008","text":"金牛山社区居委会"},{"id":"420881103009","text":"虎山社区居委会"},{"id":"420881103010","text":"丽阳居委会"},{"id":"420881103011","text":"平堰居委会"},{"id":"420881103202","text":"邱桥村委会"},{"id":"420881103203","text":"泉口村委会"},{"id":"420881103204","text":"向岗村委会"},{"id":"420881103205","text":"孙湾村委会"},{"id":"420881103206","text":"湖山村委会"},{"id":"420881103208","text":"大竹园村委会"},{"id":"420881103209","text":"石岩村委会"},{"id":"420881103210","text":"周棚村委会"},{"id":"420881103211","text":"杨店村委会"},{"id":"420881103212","text":"新泉村委会"},{"id":"420881103213","text":"张湾村委会"},{"id":"420881103214","text":"小山村委会"},{"id":"420881103215","text":"福泉村委会"},{"id":"420881103217","text":"李岗村委会"},{"id":"420881103218","text":"金岗村委会"},{"id":"420881103219","text":"黄泥村委会"},{"id":"420881103220","text":"刘湾村委会"},{"id":"420881103221","text":"尹湾村委会"},{"id":"420881103222","text":"陡堰村委会"},{"id":"420881103223","text":"五里村委会"},{"id":"420881103224","text":"任庄村委会"},{"id":"420881103225","text":"周岗村委会"},{"id":"420881103226","text":"濠沟村委会"},{"id":"420881103227","text":"红庙村委会"},{"id":"420881103228","text":"罗山村委会"},{"id":"420881103229","text":"尚湾村委会"},{"id":"420881103230","text":"彭湾村委会"},{"id":"420881103231","text":"长岗村委会"},{"id":"420881103232","text":"新岗村委会"},{"id":"420881103233","text":"蛮河村委会"},{"id":"420881103234","text":"王营村委会"},{"id":"420881103235","text":"周营村委会"},{"id":"420881103236","text":"陈营村委会"},{"id":"420881103237","text":"关山村委会"},{"id":"420881103239","text":"夏集村委会"},{"id":"420881103240","text":"邹湖村委会"},{"id":"420881103241","text":"赵河村委会"},{"id":"420881103242","text":"游湖村委会"},{"id":"420881103243","text":"杨台村委会"},{"id":"420881103244","text":"邹市村委会"},{"id":"420881103245","text":"赵集村委会"}]