[{"id":"441624104001","text":"街道居委会"},{"id":"441624104201","text":"黄沙村委会"},{"id":"441624104202","text":"江口村委会"},{"id":"441624104203","text":"百龙村委会"},{"id":"441624104204","text":"寨西村委会"},{"id":"441624104205","text":"下陵村委会"},{"id":"441624104206","text":"三乐村委会"},{"id":"441624104207","text":"富良村委会"},{"id":"441624104208","text":"新民村委会"},{"id":"441624104209","text":"丰溪村委会"},{"id":"441624104210","text":"中洞村委会"},{"id":"441624104211","text":"翠山村委会"},{"id":"441624104212","text":"上陵村委会"},{"id":"441624104213","text":"米福村委会"},{"id":"441624104214","text":"瑞州村委会"},{"id":"441624104215","text":"罗村村委会"},{"id":"441624104216","text":"桃源村委会"},{"id":"441624104217","text":"增公村委会"}]