[{"id":"511025106001","text":"和平街社区居委会"},{"id":"511025106002","text":"交通街社区居委会"},{"id":"511025106003","text":"顺江街社区居委会"},{"id":"511025106004","text":"泉江社区居委会"},{"id":"511025106201","text":"田布沟村委会"},{"id":"511025106202","text":"双堰塘村委会"},{"id":"511025106203","text":"大佛沟村委会"},{"id":"511025106204","text":"插花坪村委会"},{"id":"511025106205","text":"何家沟村委会"},{"id":"511025106206","text":"马鞍山村委会"},{"id":"511025106207","text":"太和桥村委会"},{"id":"511025106208","text":"松山坪村委会"},{"id":"511025106209","text":"小黑山子村委会"},{"id":"511025106210","text":"张家桥村委会"},{"id":"511025106211","text":"五里沟村委会"},{"id":"511025106212","text":"甑子坝村委会"},{"id":"511025106213","text":"大黑山子村委会"},{"id":"511025106214","text":"黄沙坡村委会"},{"id":"511025106215","text":"太平嘴村委会"},{"id":"511025106216","text":"雷打坡村委会"},{"id":"511025106217","text":"大树坳村委会"},{"id":"511025106218","text":"高坳村委会"},{"id":"511025106219","text":"尖山子村委会"},{"id":"511025106220","text":"翠流村委会"},{"id":"511025106221","text":"团柏村委会"},{"id":"511025106222","text":"高店子村委会"},{"id":"511025106223","text":"牌坊沟村委会"},{"id":"511025106224","text":"叶家山村委会"},{"id":"511025106225","text":"九廉寺村委会"},{"id":"511025106226","text":"界牌村委会"},{"id":"511025106227","text":"庙儿山村委会"},{"id":"511025106228","text":"鸡公山村委会"},{"id":"511025106229","text":"油房湾村委会"}]