[{"id":"513422100000","text":"乔瓦镇"},{"id":"513422101000","text":"瓦厂镇"},{"id":"513422102000","text":"茶布朗镇"},{"id":"513422103000","text":"雅砻江镇"},{"id":"513422201000","text":"博科乡"},{"id":"513422202000","text":"宁朗乡"},{"id":"513422203000","text":"依吉乡"},{"id":"513422204000","text":"俄亚纳西族乡"},{"id":"513422205000","text":"水洛乡"},{"id":"513422206000","text":"牦牛坪乡"},{"id":"513422207000","text":"屋脚蒙古族乡"},{"id":"513422208000","text":"项脚蒙古族乡"},{"id":"513422209000","text":"李子坪乡"},{"id":"513422210000","text":"列瓦乡"},{"id":"513422211000","text":"芽祖乡"},{"id":"513422212000","text":"下麦地乡"},{"id":"513422213000","text":"西秋乡"},{"id":"513422214000","text":"克尔乡"},{"id":"513422215000","text":"白碉苗族乡"},{"id":"513422216000","text":"三桷桠乡"},{"id":"513422217000","text":"倮波乡"},{"id":"513422218000","text":"卡拉乡"},{"id":"513422219000","text":"后所乡"},{"id":"513422220000","text":"沙湾乡"},{"id":"513422222000","text":"固增苗族乡"},{"id":"513422223000","text":"麦日乡"},{"id":"513422224000","text":"东朗乡"},{"id":"513422225000","text":"唐央乡"},{"id":"513422226000","text":"博窝乡"}]