[{"id":"513436100000","text":"巴普镇"},{"id":"513436200000","text":"觉洛乡"},{"id":"513436201000","text":"井叶特西乡"},{"id":"513436202000","text":"合姑洛乡"},{"id":"513436203000","text":"巴古乡"},{"id":"513436204000","text":"农作乡"},{"id":"513436205000","text":"佐戈依达乡"},{"id":"513436206000","text":"子威乡"},{"id":"513436207000","text":"依洛拉达乡"},{"id":"513436208000","text":"典补乡"},{"id":"513436209000","text":"哈洛乡"},{"id":"513436210000","text":"牛牛坝乡"},{"id":"513436211000","text":"尔合乡"},{"id":"513436212000","text":"竹库乡"},{"id":"513436213000","text":"候古莫乡"},{"id":"513436214000","text":"候播乃拖乡"},{"id":"513436215000","text":"采红乡"},{"id":"513436216000","text":"苏洛乡"},{"id":"513436217000","text":"九口乡"},{"id":"513436218000","text":"洛俄依甘乡"},{"id":"513436219000","text":"拉木阿觉乡"},{"id":"513436220000","text":"洛莫依达乡"},{"id":"513436221000","text":"柳洪乡"},{"id":"513436222000","text":"乐约乡"},{"id":"513436223000","text":"尔其乡"},{"id":"513436224000","text":"瓦古乡"},{"id":"513436225000","text":"峨曲古乡"},{"id":"513436226000","text":"炳途乡"},{"id":"513436227000","text":"拖木乡"},{"id":"513436228000","text":"尼哈乡"},{"id":"513436229000","text":"龙门乡"},{"id":"513436230000","text":"依果觉乡"},{"id":"513436231000","text":"洒库乡"},{"id":"513436232000","text":"瓦西乡"},{"id":"513436233000","text":"树窝乡"},{"id":"513436234000","text":"龙窝乡"}]