[{"id":"532932105201","text":"彭屯村委会"},{"id":"532932105202","text":"板桥村委会"},{"id":"532932105203","text":"母屯村委会"},{"id":"532932105204","text":"新民村委会"},{"id":"532932105205","text":"新华村委会"},{"id":"532932105206","text":"罗伟邑村委会"},{"id":"532932105207","text":"太平村委会"},{"id":"532932105208","text":"田屯村委会"},{"id":"532932105209","text":"小水美村委会"},{"id":"532932105210","text":"石朵河村委会"},{"id":"532932105211","text":"柳绿河村委会"},{"id":"532932105212","text":"倒流箐村委会"},{"id":"532932105213","text":"里习吉村委会"},{"id":"532932105214","text":"马厂村委会"},{"id":"532932105215","text":"新峰村委会"},{"id":"532932105216","text":"安乐村委会"}]