[{"id":"621002100200","text":"肖金村委会"},{"id":"621002100201","text":"三不同村委会"},{"id":"621002100202","text":"小寨村委会"},{"id":"621002100203","text":"张庄村委会"},{"id":"621002100204","text":"老山村委会"},{"id":"621002100205","text":"芮岭村委会"},{"id":"621002100206","text":"贺咀村委会"},{"id":"621002100207","text":"米王村委会"},{"id":"621002100208","text":"李城村委会"},{"id":"621002100209","text":"王庄村委会"},{"id":"621002100210","text":"脱坳村委会"},{"id":"621002100211","text":"胡同村委会"},{"id":"621002100212","text":"杨咀村委会"},{"id":"621002100213","text":"上刘村委会"},{"id":"621002100214","text":"南李村委会"},{"id":"621002100215","text":"左咀村委会"},{"id":"621002100216","text":"纸坊村委会"},{"id":"621002100217","text":"双桐村委会"}]