[{"id":"652923106001","text":"阿克提其居委会"},{"id":"652923106002","text":"亚贝希居委会"},{"id":"652923106003","text":"乌尊社区居民委员会"},{"id":"652923106004","text":"园艺场社区"},{"id":"652923106202","text":"英尼和村委会"},{"id":"652923106203","text":"乌尊一村委会"},{"id":"652923106204","text":"乌尊二村委会"},{"id":"652923106205","text":"乌尊艾日克村委会"},{"id":"652923106206","text":"英吐尔一村委会"},{"id":"652923106207","text":"英吐尔二村委会"},{"id":"652923106208","text":"博斯坦村委会"},{"id":"652923106209","text":"布喀其村委会"},{"id":"652923106210","text":"玉其喀拉一村委会"},{"id":"652923106211","text":"玉其喀拉二村委会"},{"id":"652923106212","text":"果勒日克村委会"},{"id":"652923106213","text":"库木艾日克村委会"},{"id":"652923106214","text":"塔格其村委会"},{"id":"652923106215","text":"色根苏盖提一村委会"},{"id":"652923106216","text":"色根苏盖提二村委会"},{"id":"652923106217","text":"色根苏盖提三村委会"},{"id":"652923106218","text":"色根苏盖提四村委会"},{"id":"652923106219","text":"克其勒克农场村委会"}]