[{"id":"310118002001","text":"庆华社区居委会"},{"id":"310118002002","text":"庆新社区居委会"},{"id":"310118002003","text":"城北社区居委会"},{"id":"310118002004","text":"龙威社区居委会"},{"id":"310118002005","text":"复兴社区居委会"},{"id":"310118002006","text":"解放社区居委会"},{"id":"310118002007","text":"西部花苑社区居委会"},{"id":"310118002008","text":"尚美社区居委会"},{"id":"310118002009","text":"万寿社区居委会"},{"id":"310118002010","text":"盈港社区居委会"},{"id":"310118002011","text":"盈中社区居委会"},{"id":"310118002012","text":"三元河社区居委会"},{"id":"310118002013","text":"盈联社区居委会"},{"id":"310118002014","text":"民乐社区居委会"},{"id":"310118002015","text":"民佳社区居委会"},{"id":"310118002016","text":"绿舟社区居委会"},{"id":"310118002017","text":"上达社区居委会"},{"id":"310118002018","text":"浩泽社区居委会"},{"id":"310118002019","text":"民欣社区居委会"},{"id":"310118002020","text":"华浦社区居委会"},{"id":"310118002021","text":"怡澜社区居委会"},{"id":"310118002022","text":"双桥社区居委会"},{"id":"310118002023","text":"东渡社区居委会"},{"id":"310118002024","text":"赵屯浦社区居委会"},{"id":"310118002025","text":"崧子浦社区居委会"},{"id":"310118002026","text":"贺桥社区居委会"},{"id":"310118002202","text":"贺桥村村委会"},{"id":"310118002203","text":"南厍村村委会"},{"id":"310118002204","text":"俞家埭村村委会"},{"id":"310118002205","text":"天恩桥村村委会"},{"id":"310118002206","text":"南横村村委会"}]