[{"id":"610304116001","text":"法士特社区居民委员会"},{"id":"610304116200","text":"程家崖村村民委员会"},{"id":"610304116201","text":"梁家崖村村民委员会"},{"id":"610304116202","text":"乙家崖村村民委员会"},{"id":"610304116203","text":"高崖村村民委员会"},{"id":"610304116204","text":"张家村村民委员会"},{"id":"610304116206","text":"北村村民委员会"},{"id":"610304116207","text":"南村村民委员会"},{"id":"610304116208","text":"颉头村村民委员会"},{"id":"610304116209","text":"寨子洼村村民委员会"},{"id":"610304116210","text":"圪塔沟村村民委员会"},{"id":"610304116211","text":"莫家洼村村民委员会"},{"id":"610304116212","text":"大湾沟村村民委员会"},{"id":"610304116213","text":"高桥沟村村民委员会"},{"id":"610304116214","text":"朱家滩村村民委员会"},{"id":"610304116215","text":"东崖村村民委员会"},{"id":"610304116216","text":"西崖村村民委员会"},{"id":"610304116218","text":"谭庄村村民委员会"},{"id":"610304116219","text":"金台村村民委员会"},{"id":"610304116220","text":"西洼村村民委员会"},{"id":"610304116221","text":"东洼村村民委员会"},{"id":"610304116222","text":"东风村村民委员会"},{"id":"610304116223","text":"东阳村村民委员会"},{"id":"610304116224","text":"红星村村民委员会"},{"id":"610304116225","text":"西塬村村民委员会"}]