[{"id":"130982203201","text":"三杰村委会"},{"id":"130982203202","text":"守练村委会"},{"id":"130982203203","text":"阁辛庄村委会"},{"id":"130982203204","text":"大征村委会"},{"id":"130982203205","text":"大街村委会"},{"id":"130982203206","text":"西南庄村委会"},{"id":"130982203207","text":"李村村委会"},{"id":"130982203208","text":"程村村委会"},{"id":"130982203209","text":"魏村村委会"},{"id":"130982203210","text":"田庄村委会"},{"id":"130982203211","text":"三坊村委会"},{"id":"130982203212","text":"石村村委会"},{"id":"130982203213","text":"东张各庄村委会"},{"id":"130982203214","text":"东长洋村委会"},{"id":"130982203215","text":"东大坞村委会"},{"id":"130982203216","text":"孙家务村委会"},{"id":"130982203217","text":"陈村村委会"},{"id":"130982203218","text":"野王庄村委会"},{"id":"130982203219","text":"东庄店村委会"},{"id":"130982203220","text":"小门村委会"},{"id":"130982203221","text":"邢村村委会"}]