[{"id":"140108008001","text":"柴村社区居委会"},{"id":"140108008002","text":"摄乐社区居委会"},{"id":"140108008003","text":"三给社区居委会"},{"id":"140108008004","text":"营村社区居委会"},{"id":"140108008005","text":"芮城社区居委会"},{"id":"140108008006","text":"柴村中心社区居委会"},{"id":"140108008200","text":"大留村村委会"},{"id":"140108008201","text":"呼延村村委会"},{"id":"140108008202","text":"西张村村委会"},{"id":"140108008203","text":"杨家村村委会"},{"id":"140108008209","text":"小石河村委会"},{"id":"140108008210","text":"寺头村委会"},{"id":"140108008211","text":"小塔村委会"},{"id":"140108008212","text":"下槐村委会"},{"id":"140108008213","text":"柏崖头村委会"}]