[{"id":"140522107200","text":"河北村委会"},{"id":"140522107201","text":"土孟村委会"},{"id":"140522107202","text":"下交村委会"},{"id":"140522107203","text":"匠礼村委会"},{"id":"140522107206","text":"元岭村委会"},{"id":"140522107207","text":"圪桃窊村委会"},{"id":"140522107208","text":"南梁村委会"},{"id":"140522107209","text":"北梁村委会"},{"id":"140522107211","text":"史家岭村委会"},{"id":"140522107212","text":"炭窑村委会"},{"id":"140522107213","text":"九甲村委会"},{"id":"140522107215","text":"赵沟村委会"},{"id":"140522107216","text":"孤堆底村委会"},{"id":"140522107217","text":"西头村委会"},{"id":"140522107218","text":"洞底村委会"},{"id":"140522107220","text":"圪涝掌村委会"},{"id":"140522107221","text":"坪泉村委会"},{"id":"140522107225","text":"东交村委会"},{"id":"140522107227","text":"西交村委会"},{"id":"140522107229","text":"杨柏村委会"}]