[{"id":"140723101200","text":"南李阳村委会"},{"id":"140723101201","text":"后峪村委会"},{"id":"140723101202","text":"回黄村委会"},{"id":"140723101203","text":"温源村委会"},{"id":"140723101204","text":"榆圪塔村委会"},{"id":"140723101206","text":"泊里村委会"},{"id":"140723101208","text":"上石勒村委会"},{"id":"140723101211","text":"下石勒村委会"},{"id":"140723101212","text":"三奇村委会"},{"id":"140723101213","text":"三奇掌村委会"},{"id":"140723101214","text":"北李阳村委会"},{"id":"140723101220","text":"蝉窑沟村委会"},{"id":"140723101221","text":"野狐坪村委会"},{"id":"140723101223","text":"郭家垴村委会"},{"id":"140723101224","text":"秦家庄村委会"},{"id":"140723101225","text":"上丰村委会"},{"id":"140723101227","text":"史家庄村委会"},{"id":"140723101228","text":"天井村委会"},{"id":"140723101229","text":"常家庄村委会"},{"id":"140723101230","text":"岩庄吉村委会"}]