[{"id":"511802101001","text":"草坝社区居委会"},{"id":"511802101200","text":"草坝村委会"},{"id":"511802101201","text":"新时村委会"},{"id":"511802101202","text":"河岗村委会"},{"id":"511802101203","text":"幸福村委会"},{"id":"511802101204","text":"林口村委会"},{"id":"511802101205","text":"石坪村委会"},{"id":"511802101206","text":"水口村委会"},{"id":"511802101207","text":"栗子村委会"},{"id":"511802101208","text":"均田村委会"},{"id":"511802101209","text":"水津村委会"},{"id":"511802101210","text":"金沙村委会"},{"id":"511802101211","text":"香花村委会"},{"id":"511802101212","text":"广华村委会"},{"id":"511802101213","text":"飞梁村委会"},{"id":"511802101214","text":"清溪村委会"},{"id":"511802101215","text":"石桥村委会"},{"id":"511802101216","text":"洪川村委会"}]